flask_minify/__init__.py
flask_minify/about.py
flask_minify/cache.py
flask_minify/decorators.py
flask_minify/exceptions.py
flask_minify/main.py
flask_minify/parsers.py
flask_minify/utils.py
Flask_Minify-0.48.dist-info/LICENSE
Flask_Minify-0.48.dist-info/METADATA
Flask_Minify-0.48.dist-info/WHEEL
Flask_Minify-0.48.dist-info/top_level.txt
Flask_Minify-0.48.dist-info/RECORD
