Metadata-Version: 2.1
Name: Flask-Minify
Version: 0.48
Summary: Flask extension to minify html, css, js and less.
Home-page: https://github.com/mrf345/flask_minify/
Download-URL: https://github.com/mrf345/flask_minify/archive/0.48.tar.gz
Author: Mohamed Feddad
Author-email: mrf345@gmail.com
License: MIT
Keywords: flask,extension,minifer,htmlmin,lesscpy,jsmin,html,js,less,css
Platform: any
Classifier: Programming Language :: Python :: 3.7
Classifier: Programming Language :: Python :: 3.8
Classifier: Programming Language :: Python :: 3.9
Classifier: Programming Language :: Python :: 3.10
Classifier: Programming Language :: Python :: 3.11
Classifier: Programming Language :: Python :: 3.12
Classifier: Environment :: Web Environment
Classifier: Intended Audience :: Developers
Classifier: License :: OSI Approved :: MIT License
Classifier: Operating System :: OS Independent
Classifier: Programming Language :: Python
Classifier: Topic :: Internet :: WWW/HTTP :: Dynamic Content
Classifier: Topic :: Software Development :: Libraries :: Python Modules
Provides-Extra: go
License-File: LICENSE
